pymodaq_utils/__init__.py
pymodaq_utils/abstract.py
pymodaq_utils/array_manipulation.py
pymodaq_utils/config.py
pymodaq_utils/enums.py
pymodaq_utils/environment.py
pymodaq_utils/factory.py
pymodaq_utils/icon.ico
pymodaq_utils/logger.py
pymodaq_utils/math_utils.py
pymodaq_utils/mysocket.py
pymodaq_utils/splash.png
pymodaq_utils/units.py
pymodaq_utils/utils.py
pymodaq_utils/warnings.py
pymodaq_utils/resources/__init__.py
pymodaq_utils/resources/config_template.toml
pymodaq_utils/resources/hatch_build_plugins.py
pymodaq_utils/serialize/__init__.py
pymodaq_utils/serialize/factory.py
pymodaq_utils/serialize/mysocket.py
pymodaq_utils/serialize/serializer.py
pymodaq_utils/serialize/serializer_legacy.py
pymodaq_utils/serialize/utils.py
pymodaq_utils-5.1.7.dist-info/METADATA
pymodaq_utils-5.1.7.dist-info/WHEEL
pymodaq_utils-5.1.7.dist-info/licenses/LICENSE
pymodaq_utils-5.1.7.dist-info/RECORD
